mnist/__init__.py
mnist/cli.py
mnist/contest.py
mnist/gui.py
mnist/lib.py
mnist/net.py
mnist/svm.py
mnist/toy.py
mnist/data/mnist.pkl.gz
mnist/data/mnist_net_model.gz
mnist/data/mnist_svm_model.gz
mnist/data/report.json.gz
mnist_hub-0.1.4.dist-info/METADATA
mnist_hub-0.1.4.dist-info/WHEEL
mnist_hub-0.1.4.dist-info/entry_points.txt
mnist_hub-0.1.4.dist-info/top_level.txt
mnist_hub-0.1.4.dist-info/RECORD
