Metadata-Version: 2.2
Name: mnist-hub
Version: 0.1.4
Author: Istvan Albert
Requires-Python: >=3.10
Requires-Dist: numpy<2.0.0
Requires-Dist: scikit-learn
Requires-Dist: click
Requires-Dist: scipy
Requires-Dist: Pillow
